{
    "_login_screen": "Შესვლა",
    "login_txt_login": "Შესვლა",
    "login_txt_login_now": "Შედით ახლა",
    "login_btn_login": "Შებრძანდით",
    "login_txt_register": "რეგისტრაცია",
    "login_txt_register_now": "Დარეგისტრირდით ახლა",
    "login_btn_create_account": "Შექმენი ანგარიში",
    "login_btn_register": "რეგისტრაცია",
    "login_text_or": "ან",
    "login_btn_forgot_password": "Დაგავიწყდა შენი პაროლი?",
    "login_description_register": "არ გაქვთ ანგარიში?",
    "login_description_social": "შექმენით ანგარიში გასაგრძელებლად",
    "login_sign_in_to_receive": "შედით, რომ მიიღოთ ექსკლუზიური შეთავაზებები და\nაქციები",
    "login_local_let_os": "მიეცით OS-მა განსაზღვროს ავტორიზაციის მეთოდი",
    "login_local_scan_face": "დაასკანირეთ თქვენი სახე ავთენტიფიკაციისთვის",
    "login_local_scan_iris": "დაასკანირეთ თქვენი ირისი ავთენტიფიკაციისთვის",
    "login_local_scan_fingerprint": "დაასკანირეთ თქვენი თითის ანაბეჭდი ავთენტიფიკაციისთვის",
    "login_local_using_biometric": "ბიომეტრიის გამოყენება",
    "_register_screen": "რეგისტრაცია",
    "input_user_email": "მომხმარებლის სახელი ან ელექტრონული ფოსტის მისამართი",
    "input_first_name_required": "Სახელი *",
    "input_last_name_required": "Გვარი *",
    "input_username_required": "მომხმარებლის სახელი *",
    "input_phone_number_required": "Ტელეფონის ნომერი *",
    "input_email_required": "ელფოსტა *",
    "input_password_required": "პაროლი *",
    "input_password": "პაროლი",
    "input_email": "ელფოსტა",
    "input_name": "სახელი",
    "register_app_bar_title": "რეგისტრაცია",
    "register_btn_submit": "რეგისტრაცია",
    "register_btn_login": "Უკვე გაქვთ ანგარიში ?",
    "_login_mobile_screen": "შესვლის ტელეფონის ნომერი",
    "login_mobile_appbar": "შესვლა მობილური",
    "login_mobile_description": "შედით თქვენი ტელეფონის ნომრით",
    "login_mobile_btn_code": "Კოდის მიღება",
    "login_mobile_title_verify": "გადამოწმება",
    "login_mobile_description_code": "დაიბრუნო OTP?",
    "login_mobile_btn_send": "ᲮᲔᲚᲐᲮᲚᲐ ᲒᲐᲒᲖᲐᲕᲜᲐ",
    "login_mobile_btn_verify": "გადაამოწმეთ ახლა",
    "login_mobile_error": "არასწორი OTP შევიდა",
    "login_mobile_count_down": "ხელახლა გაგზავნეთ OTP შემდეგში: {_start} წმ",
    "_edit_account_screen": "ანგარიში",
    "edit_account_my_account": "Ჩემი ანგარიში",
    "edit_account_your_account": "Თქვენი ანგარიში",
    "edit_account": "ანგარიშის რედაქტირება",
    "edit_account_first_name": "Სახელი *",
    "edit_account_last_name": "Გვარი *",
    "edit_account_display_name": "Ჩვენების სახელი *",
    "edit_account_email_address": "Ელექტრონული მისამართი *",
    "edit_account_first_name_required": "სახელი სავალდებულოა",
    "edit_account_last_name_required": "გვარი სავალდებულოა",
    "edit_account_display_name_required": "საჩვენებელი სახელი აუცილებელია",
    "edit_account_email_required": "ელ.ფოსტა აუცილებელია",
    "edit_account_save": "Გადარჩენა",
    "_delete_account_screen": "Ანგარიშის წაშლა",
    "delete_account_txt": "Ანგარიშის წაშლა",
    "delete_account_reason_description": "ვწუხვართ, რომ გინდოდათ თქვენი ანგარიშის წაშლა. აცნობეთ ცირილას რატომ!",
    "delete_account_reason_dropdown_label": "მიზეზი",
    "delete_account_reason_dropdown_placeholder": "რატომ გსურთ თქვენი ანგარიშის წაშლა?",
    "delete_account_reason_option_email": "მინდა შევცვალო ელ.ფოსტა ან ტელეფონის ნომერი",
    "delete_account_reason_option_review": "მსურს ჩემი ანგარიშის მიმოხილვების ან შესყიდვების ისტორიის რედაქტირება",
    "delete_account_reason_option_use": "არ მინდა Cirilla-ს გამოყენების გაგრძელება",
    "delete_account_reason_option_other": "სხვა",
    "delete_account_reason_button": "აირჩიეთ",
    "delete_account_term_title": "Cirilla ბოდიშს გიხდით, რომ თქვენ მაინც აირჩიეთ თქვენი ანგარიშის წაშლა.",
    "delete_account_term_subtitle": "გთხოვთ, ყურადღებით წაიკითხოთ ჩვენი წესები და პირობები წაშლამდე.",
    "delete_account_term_post": "თქვენი პოსტები წაიშლება და ვერ აღდგება",
    "delete_account_term_comment": "თქვენი კომენტარები წაიშლება და ვერ აღდგება",
    "delete_account_term_order": "შეკვეთები უნდა დასრულდეს ანგარიშის წაშლამდე",
    "delete_account_term_cancel": "გაუქმება",
    "delete_account_term_next": "შემდეგი",
    "delete_account_agree_title": "დარწმუნებული ხართ, რომ გსურთ თქვენი ანგარიშის წაშლა?",
    "delete_account_agree_subtitle": "შეამოწმეთ ქვემოთ მოცემული ველი, თუ დარწმუნებული ხართ, რომ გსურთ წაშლა",
    "delete_account_agree_checkbox": "მე ნამდვილად მინდა ჩემი Cirilla ანგარიშის წაშლა",
    "delete_account_agree_cancel": "გაუქმება",
    "delete_account_agree_send": "გაგზავნა",
    "delete_account_otp_title": "შეიყვანეთ დამადასტურებელი კოდი",
    "delete_account_otp_subtitle": "იმისთვის, რომ დაადასტუროთ, რომ ელფოსტა თქვენია, შეიყვანეთ 6-ციფრიანი კოდი, რომელზეც ახლახან გაიგზავნა",
    "delete_account_otp_send_success": "ხელახლა გაგზავნეთ წარმატება. გთხოვთ შეამოწმოთ თქვენი ფოსტა",
    "delete_account_success_title": "ანგარიშის წარმატებით წაშლა",
    "delete_account_success_subtitle": "გმადლობთ ცირილას თანხლებისთვის. ძალიან გვენატრებით. არ დაგავიწყდეთ ცირილა ყოველთვის აქ არის, როცა დაგჭირდებათ.",
    "delete_account_success_button": "სრული",
    "_change_phone_screen": "ტელეფონის ნომრის შეცვლა",
    "change_phone": "ტელეფონის შეცვლა",
    "_forgot_password_screen": "Დაგავიწყდა შენი პაროლი",
    "forgot_password_appbar": "Დაგავიწყდა შენი პაროლი",
    "forgot_password_description": "შეიყვანეთ თქვენი ანგარიშის ელფოსტის მისამართი და ჩვენ გამოგიგზავნით ინსტრუქციებს თქვენი პაროლის აღდგენის შესახებ",
    "forgot_password_desc_app": "გთხოვთ, შეიყვანოთ თქვენი მომხმარებლის სახელი დადასტურების კოდის მისაღებად. ჩვენ გამოგიგზავნით კოდს ელ.ფოსტის მისამართზე, რომელიც რეგისტრირებულია თქვენს ანგარიშზე.",
    "forgot_password_note": "შენიშვნა: თქვენი ელ.ფოსტის მისამართი უნდა იყოს მოქმედი და არ დაგავიწყდეთ შეამოწმოთ თქვენი უსარგებლო შემომავალი.",
    "forgot_password": "გაგზავნა",
    "forgot_password_reset_password": "პაროლის აღდგენა",
    "forgot_password_btn": "ელ.ფოსტის გაგზავნა",
    "forgot_password_success": "გადადით თქვენს ელფოსტაზე პაროლის მისაღებად",
    "_change_password": "Პაროლის შეცვლა",
    "change_password": "Პაროლის შეცვლა",
    "change_password_old": "პაროლი *",
    "change_password_new": "Ახალი პაროლი *",
    "change_password_confirm": "Პაროლის დადასტურება *",
    "change_password_old_required": "საჭიროა პაროლი",
    "change_password_new_required": "საჭიროა ახალი პაროლი",
    "change_password_confirm_required": "საჭიროა პაროლის დადასტურება",
    "change_password_new_diff_old": "ახალი პაროლი უნდა განსხვავდებოდეს პაროლისგან",
    "change_password_confirm_same_new": "დაადასტურეთ, რომ პაროლი იგივე უნდა იყოს ახალი პაროლიდან",
    "change_password_save": "Გადარჩენა",
    "_validate_screen": "დადასტურება",
    "validate_user_email_required": "მომხმარებლის სახელი აუცილებელია.",
    "validate_first_name_required": "სახელი აუცილებელია.",
    "validate_last_name_required": "გვარი აუცილებელია.",
    "validate_username_required": "მომხმარებლის სახელი აუცილებელია.",
    "validate_phone_number_required": "საჭიროა ტელეფონის ნომერი.",
    "validate_email_required": "საჭიროა ელ.ფოსტა.",
    "validate_space": "Არ არის ადგილი",
    "validate_characters_in_length": "უნდა იყოს მინიმუმ {length} სიმბოლო სიგრძით.",
    "validate_one_upper_case": "უნდა შეიცავდეს მინიმუმ ერთ ზედა რეზონანს.",
    "validate_one_lower_case": "უნდა შეიცავდეს მინიმუმ ერთ მცირე ასოს.",
    "validate_one_digit": "უნდა შეიცავდეს მინიმუმ ერთ ციფრს.",
    "validate_one_special_character": "უნდა შეიცავდეს მინიმუმ ერთ სპეციალურ სიმბოლოს.",
    "validate_without_special_characters": "სპეციალური პერსონაჟების გარეშე",
    "validate_password_required": "საჭიროა პაროლი.",
    "validate_review_required": "საჭიროა შინაარსის შეფასება.",
    "validate_name_required": "სახელი აუცილებელია.",
    "validate_country_required": "ქვეყანა აუცილებელია.",
    "validate_state_required": "სახელმწიფოა საჭირო.",
    "validate_address1_required": "საჭიროა მისამართი 1.",
    "validate_city_required": "ქალაქი აუცილებელია.",
    "validate_postcode_required": "საფოსტო კოდი აუცილებელია.",
    "validate_phone_required": "ტელეფონი აუცილებელია.",
    "validate_email_value": "არა მისამართის ელფოსტა",
    "validate_phone_value": "ტელეფონის ნომერი არა",
    "validate_not_null": "Აუცილებელი ველი",
    "validate_not_int": "არა ნომერი",
    "validate_int_min": "უნდა &gt;= {min}",
    "validate_int_max": "უნდა &lt;= {max}",
    "_product_screen": "პროდუქტი",
    "product_description": "აღწერა",
    "product_addition_information": "დამატებითი ინფორმაცია",
    "product_reviews": "მიმოხილვები",
    "product_all_reviews": "ყველა მიმოხილვა",
    "product_count_reviews": "{count} მიმოხილვა",
    "product_count_review": "{count} მიმოხილვა",
    "product_star_review": "{visit} ვარსკვლავი",
    "product_write_review": "დაწერეთ მიმოხილვა",
    "product_tab_star": "ჩანართი ვარსკვლავისთვის",
    "product_submit_review": "გაგზავნა",
    "product_related": "მსგავსი პროდუქტები",
    "product_sku": "Sku: {sku}",
    "product_add_to_cart": "Კალათაში დამატება",
    "product_buy_product": "შეიძინეთ პროდუქტი",
    "product_add_to_cart_success": "კალათაში წარმატებით დამატება.",
    "product_add_to_cart_error_option": "გთხოვთ, აირჩიოთ პროდუქტის რამდენიმე ვარიანტი ამ პროდუქტის თქვენს კალათაში დამატებამდე.",
    "product_add_to_cart_error_group": "გთხოვთ, აირჩიოთ საქონლის რაოდენობა, რომლის დამატება გსურთ თქვენს კალათაში…",
    "product_add_to_cart_error_appointment": "გთხოვთ, აირჩიოთ საქონელი, რომელიც გსურთ დაამატოთ თქვენს კალათაში…",
    "product_clear_all": "Ყველაფრის გასუფთავება",
    "product_status_backorder": "შეკვეთით",
    "product_status_outstock": "Არ არის საწყობში",
    "product_status_instock": "Საწყობში",
    "product_status_instock_count": "{count} მარაგში",
    "product_sold_count": "გაიყიდა {count}",
    "product_buy_now": "Იყიდე ეხლა",
    "product_from": "დან",
    "product_new": "ახალი",
    "product_sale": "გაყიდვა",
    "product_quantity_max": "ამ ნივთისთვის დარჩენილია მხოლოდ {max} რაოდენობა",
    "product_quantity_min": "მნიშვნელობა უნდა იყოს {min} ზე მეტი ან ტოლი.",
    "product_remove_title": "გსურთ წაშალოთ &quot; {name} &quot;?",
    "product_remove_cancel": "გაუქმება",
    "product_remove_ok": "კარგი",
    "product_quantity_agree": "ვეთანხმები",
    "product_brand": "ბრენდი:",
    "product_upsell": "ასევე შეიძლება მოგეწონოთ…",
    "product_no": "პროდუქტი არ არის",
    "product_you_currently": "თქვენ ამჟამად არ გაქვთ პროდუქტი",
    "product_back": "უკან",
    "product_select_options": "აირჩიეთ პარამეტრები",
    "product_select_option": "აირჩიეთ ვარიანტი...",
    "product_none": "არცერთი",
    "product_message_addon": "გთხოვთ, შეამოწმოთ ველები",
    "product_addon_single_choice": "აირჩიეთ ეს ვარიანტი",
    "product_addon_checkbox": "აირჩიეთ ეს პარამეტრები",
    "product_addon_text": "შეავსეთ ეს ველი",
    "product_addon_letter": "მხოლოდ ასოები",
    "product_addon_number": "მხოლოდ ნომერი",
    "product_addon_letter_number": "მხოლოდ ასოები და რიცხვები",
    "product_addon_email": "მხოლოდ ფოსტა",
    "product_addon_compare_number": "უნდა {compare} {value}",
    "product_appointment_no_preference": "არავითარი უპირატესობა",
    "product_appointment_morning": "დილა",
    "product_appointment_afternoon": "შუადღე",
    "product_appointment_evening": "საღამო",
    "product_view_cart": "Კალათის ნახვა",
    "product_appointment_durations": "+ {duration} წუთი",
    "product_appointment_duration": "+ {duration} წუთი",
    "product_file_size": "ფაილის მაქსიმალური ზომა 1 მბ",
    "product_share": "გააზიარეთ",
    "product_hide": "დამალვა",
    "product_read_more": "Წაიკითხე მეტი",
    "product_view": "პროდუქტის ნახვა",
    "product_brands": "Ბრენდები",
    "_contact_screen": "კონტაქტი",
    "contact_us": "Დაგვიკავშირდით",
    "contact_touch": "Შემეხმიანე",
    "contact_questions": "დაგვიკავშირდით დამატებითი კითხვებისთვის, შესაძლო ბიზნეს პარტნიორობისთვის",
    "contact_mess": "შეტყობინება *",
    "contact_name": "სახელი *",
    "contact_email": "ელფოსტა *",
    "contact_submit": "გაგზავნა",
    "contact_mess_is_required": "საჭიროა შეტყობინება",
    "contact_email_is_required": "საჭიროა ელ.წერილი",
    "contact_name_is_required": "სახელი აუცილებელია",
    "_order_return_screen": "შეკვეთის დაბრუნება",
    "order_return": "შეკვეთა და დაბრუნება",
    "order_title": "შეკვეთა {id}",
    "order_billing_address": "ბილინგის მისამართი",
    "order_shipping_address": "მიწოდების მისამართი",
    "order_shipping_method": "Ტრანსპორტირების მეთოდი :",
    "order_payment_method": "Გადახდის საშუალება :",
    "order_free_shipping": "Უფასო გზავნილი",
    "order_shipping_successful": "მიწოდება წარმატებით დასრულდა",
    "order_information": "შეკვეთის ინფორმაცია",
    "order_notes": "შეუკვეთეთ განახლებები",
    "order_total": "სულ :",
    "order_email": "ელფოსტა:",
    "order_date": "თარიღი:",
    "order_number": "Შეკვეთის ნომერი :",
    "order_shipping": "Ტრანსპორტირება :",
    "order_tax": "გადასახადი:",
    "order_shipping_tax": "გადაზიდვის გადასახადი:",
    "order_discount": "ფასდაკლება:",
    "order_discount_tax": "ფასდაკლების გადასახადი:",
    "order_include": "დღგ-ს ჩათვლით",
    "order_refund": "თანხის დაბრუნება",
    "order": "შეკვეთები",
    "order_no_order_has_been_made_yet": "შეკვეთა ჯერ არ გაკეთებულა.",
    "order_return_shop": "მაღაზიაში დაბრუნება",
    "order_congrats": "Გილოცავ !",
    "order_thank_you_purchase": "გმადლობთ შეძენა.\nთქვენი შეკვეთა გამოგიგზავნეთ.",
    "order_info": "შეკვეთის ინფორმაცია",
    "order_pending": "მომლოდინე",
    "order_processing": "დამუშავება",
    "order_on_hold": "Ხელის ჩაჭიდება",
    "order_completed": "დასრულებული",
    "order_cancelled": "გაუქმდა",
    "order_refunded": "თანხის დაბრუნება",
    "order_failed": "ვერ მოხერხდა",
    "order_trash": "ნაგავი",
    "order_billing_email": "ელფოსტის მისამართი: {email}",
    "order_billing_phone": "ტელეფონი: {phone}",
    "order_not_found": "შეკვეთა ვერ მოიძებნა",
    "order_cancellation_details": "გაუქმების დეტალები",
    "order_request": "შეკვეთის გაუქმების მოთხოვნა",
    "order_cancel": "Შეკვეთის გაუქმება",
    "_download_screen": "ჩამოტვირთვა",
    "download_title": "ჩამოტვირთვები",
    "download_remain": "ქვემოთ დარჩენილი:",
    "download_expire": "ვადა იწურება:",
    "download_never": "არასოდეს",
    "download_file_name": "Ფაილის სახელი :",
    "download_completed": "{download} ჩამოტვირთვა დასრულდა",
    "_cart_screen": "კალათა",
    "cart_add_to_cart": "Კალათაში დამატება",
    "cart_count": "კალათა {count}",
    "cart_no_count": "კალათა",
    "cart_coupon": "კუპონი",
    "cart_coupon_price": "კუპონი: {price}",
    "cart_successfully": "კუპონის წარმატებით გამოყენება.",
    "cart_ship_success": "მიწოდება არჩეულია წარმატებით.",
    "cart_coupon_remove": "კუპონის წარმატებით ამოღება.",
    "cart_coupon_discount": "კუპონის ფასდაკლება",
    "cart_coupon_empty": "ცარიელი მონაცემები",
    "cart_total": "სულ",
    "cart_sub_total": "სუბტოტალი",
    "cart_code_coupon": "კუპონი: {code}",
    "cart_tax": "გადასახადი",
    "cart_shipping": "მიწოდების მისამართი",
    "cart_shipping_method": "ტრანსპორტირების მეთოდი",
    "cart_proceed_to_checkout": "გადადით Checkout-ზე",
    "cart_checkout": "გადახდა",
    "cart_apply": "მიმართეთ",
    "cart_your_bag_is_empty": "თქვენი ჩანთა ცარიელია",
    "cart_items_added_to_your_bag_will_show_up_here": "გამოჩნდება თქვენს ჩანთაში დამატებული ნივთები\nაქ მაღლა",
    "cart_return_shop": "მაღაზიაში დაბრუნება",
    "cart_is_currently_empty": "თქვენი კალათა ამჟამად ცარიელია.",
    "cart_delete_dialog_title": "კალათის წაშლა",
    "cart_delete_dialog_description": "კალათა სამუდამოდ წაიშლება.",
    "cart_delete_dialog_cancel": "გაუქმება",
    "cart_delete_dialog_ok": "კარგი",
    "cart_coupon_detail": "დეტალი",
    "cart_coupon_detail_2": "კუპონის დეტალი",
    "cart_coupon_copy": "კოპირება",
    "cart_coupon_expired": "კუპონს ვადა გაუვიდა",
    "cart_coupon_description": "კუპონის აღწერა",
    "cart_coupon_code": "Კუპონის კოდი",
    "cart_coupon_list": "კუპონების სია",
    "cart_coupon_add": "დაამატეთ კუპონი",
    "_product_list_screen": "Პროდუქტების სია",
    "product_list_products": "Ყველა პროდუქტი",
    "product_list_items": "{count} ელემენტი",
    "product_list_item": "{count} ელემენტი",
    "product_list_sort": "დალაგება",
    "product_list_refine": "დახვეწა",
    "product_list_default": "ნაგულისხმევი დახარისხება",
    "product_list_popular": "პოპულარული",
    "product_list_rating": "რეიტინგი",
    "product_list_latest": "უახლესი",
    "product_list_low_to_high": "დაბალიდან მაღალზე",
    "product_list_high_to_low": "მაღალიდან დაბალამდე",
    "product_list_select": "აირჩიეთ",
    "product_list_filters": "ფილტრები",
    "product_list_categories": "კატეგორიები",
    "product_list_clear_all": "Ყველაფრის გასუფთავება",
    "product_list_in_stock": "Საწყობში",
    "product_list_on_sale": "Იყიდება",
    "product_list_featured": "გამორჩეული",
    "product_list_view_all": "Ყველას ნახვა",
    "product_list_ranges_price": "მერყეობს ფასი",
    "product_list_apply": "მიმართეთ",
    "product_list_min_price": "მინიმალური ფასი: {price}",
    "product_list_max_price": "მაქსიმალური ფასი: {price}",
    "product_search_results": "Ძიების შედეგები",
    "product_clear": "ტექსტის გასუფთავება",
    "product": "პროდუქტები",
    "product_no_products_were_found": "შესატყვისი პროდუქტი ვერ მოიძებნა\nთქვენი არჩევანი.",
    "_address_billing_screen": "მისამართი ბილინგი",
    "address_billing": "ბილინგის მისამართი",
    "address_shipping": "მიწოდების მისამართი",
    "address_first_name": "Სახელი",
    "address_last_name": "Გვარი",
    "address_company": "კომპანიის სახელი (არასავალდებულო)",
    "address_country": "ქვეყანა/რეგიონი",
    "address_1": "მისამართის ხაზი 1",
    "address_2": "მისამართის ხაზი 2",
    "address_city": "ქალაქი",
    "address_state": "შტატის / ოლქის ან შტატის კოდი",
    "address_post_code": "საფოსტო ინდექსი",
    "address_email": "ელფოსტა",
    "address_phone": "ტელეფონი",
    "address_save": "Გადარჩენა",
    "address_update": "მისამართის განახლება",
    "address_change": "Მისამართის შეცვლა",
    "address_note": "კარგად დაგიკავშირდებით მხოლოდ ტელეფონით, თუ თქვენს შეკვეთასთან დაკავშირებული პრობლემაა",
    "address_search": "ძიება",
    "address_select_country": "აირჩიეთ ქვეყანა",
    "address_select_state": "აირჩიეთ სახელმწიფო",
    "address_billing_success": "მისამართის ბილინგი წარმატებით განაახლეთ",
    "address_shipping_success": "მისამართის მიწოდების განახლება წარმატებით",
    "address_modal_date_cancel": "გაუქმება",
    "address_modal_date_ok": "კარგი",
    "address_disable_shipping": "გამორთეთ მიწოდების და მიწოდების გამოთვლები",
    "address_empty_shipping": "მინდვრები ცარიელია",
    "address_empty_billing": "ველები ბილინგი ცარიელია",
    "_settings_screen": "პარამეტრები",
    "settings": "პარამეტრები",
    "app_settings": "აპის პარამეტრები",
    "app_settings_language": "Ენა",
    "app_settings_select_lang": "Აირჩიეთ ენა",
    "app_settings_currency": "ვალუტა",
    "app_settings_dark_theme": "მუქი თემა",
    "app_settings_connect_api": "დაკავშირება API",
    "information": "ინფორმაცია",
    "chat": "Სასაუბრო",
    "help_info": "დახმარება და ინფორმაცია",
    "hotline": "ცხელი ხაზი",
    "sign_out": "Სისტემიდან გამოსვლა",
    "welcome": "მოგესალმებით",
    "select_country": "აირჩიეთ ვალუტა",
    "sort_by": "Დალაგება",
    "refine": "დახვეწა",
    "clear_all": "Ყველაფრის გასუფთავება",
    "apply": "მიმართეთ",
    "categories": "კატეგორიები",
    "undo": "გაუქმება",
    "load_more": "Მეტის ჩატვირთვა",
    "expired": "ვადა გაუვიდა",
    "count_day": "{count} დ",
    "count_hour": "{count} სთ",
    "count_minus": "{count} მ",
    "count_second": "{count} ს",
    "sale_percent": "- {percent} %",
    "label_search_phone": "მოძებნეთ ქვეყნის სახელი",
    "select_language": "Აირჩიეთ ენა",
    "_wishlist_screen": "სურვილების სია",
    "wishlist": "სურვილების სია",
    "wishlist_notification_deleted": "{name} წაიშალა სურვილების სიიდან",
    "wishlist_undo": "გაუქმება",
    "wishlist_items": "{count} ელემენტი",
    "wishlist_empty_description": "უბრალოდ შედით სისტემაში, რომ გააგრძელოთ იქ, სადაც შეჩერდით.",
    "wishlist_return_shop": "მაღაზიაში დაბრუნება",
    "_product_review": "პროდუქტის მიმოხილვა",
    "product_review_message_success": "თქვენი განხილვა ელოდება დამტკიცებას",
    "input_review": "დაწერეთ თქვენი რეიტინგი აქ",
    "_side_bar_screen": "გვერდითი ზოლი",
    "side_bar_logout": "გამოსვლა",
    "side_bar_guest": "სტუმარი",
    "side_bar_guest_info": "სტუმრის ინფორმაცია",
    "side_bar_login_source": "შესვლა /",
    "side_bar_login": "შესვლა",
    "side_bar_sign_up": "დარეგისტრირდით",
    "_post_category_screen": "პოსტის კატეგორია",
    "post_category_search": "პოსტების ძიება",
    "post_search_results": "Ძიების შედეგები",
    "post_no_post_were_found": "შესაბამისი პოსტი ვერ მოიძებნა\nთქვენი არჩევანი.",
    "post_count": "{count} პოსტი",
    "post_count_single": "{count} პოსტი",
    "_post_author_screen": "ავტორი",
    "post_author_txt": "ავტორი",
    "post_author_articles": "{count} სტატია",
    "post_author_article": "{count} სტატია",
    "_post_list_screen": "პოსტების სია",
    "post_list_txt": "Ახალი ამბები",
    "post_list_sort_latest": "უახლესი",
    "post_list_sort_oldest": "Უძველესი",
    "post_list_tags": "ტეგები",
    "_post_detail_screen": "გამოაქვეყნეთ დეტალები",
    "post_detail_reviewbox_title": "გასაოცარია",
    "post_detail_reviewbox_description": "მოათავსეთ აქ აღწერა თქვენი განხილვის ყუთისთვის",
    "post_detail_expert_score": "საექსპერტო ქულა",
    "post_detail_offerbox_button": "შეიძინეთ ეს ნივთი",
    "post_detail_offerbox_reveal": "გამოავლინე",
    "post_detail_comparison_button": "შეამოწმეთ ფასები",
    "post_detail_comparison_list_item": "შეამოწმეთ უახლესი ფასები",
    "post_detail_positive": "პოზიტიური",
    "post_detail_negatives": "ნეგატივები",
    "post_detail_sample_title": "ნიმუშის სათაური",
    "post_detail_sample_content": "ნიმუშის შინაარსი",
    "post_detail_purchase_now": "შეიძინეთ ახლავე",
    "post_detail_buy_item": "შეიძინეთ ნივთი",
    "post_detail_versus_title": "სათაურის წინააღმდეგ",
    "post_detail_versus_subline": "ქვეხაზის წინააღმდეგ",
    "post_detail_vs": "Vs",
    "post_detail_edit_title": "დაარედაქტირე ეს სათაური",
    "post_related": "დაკავშირებული პოსტი",
    "_vendor_list_screen": "გამყიდველის სია",
    "vendor_list_txt": "ყველა გამყიდველი",
    "vendor_sort_date_asc": "დალაგება სიახლის მიხედვით: ძველიდან ახალზე",
    "vendor_sort_date_desc": "დალაგება სიახლის მიხედვით: ახალიდან ძველზე",
    "vendor_sort_rating_asc": "დალაგება საშუალო შეფასების მიხედვით: დაბალიდან მაღალზე",
    "vendor_sort_rating_desc": "დალაგება საშუალო შეფასების მიხედვით: მაღალიდან დაბალამდე",
    "vendor_sort_title_asc": "დალაგება ანბანურად: A-დან Z-მდე",
    "vendor_sort_title_desc": "დალაგება ანბანურად: Z-დან A-მდე",
    "vendor_refine_search": "იპოვეთ მაღაზიები",
    "vendor_refine_range": "Დიაპაზონი",
    "vendor_refine_distance": "{distance} კმ",
    "_vendor_detail_screen": "გამყიდველის დეტალი",
    "vendor_detail_txt": "Გამყიდველი",
    "vendor_detail_products": "პროდუქტები",
    "vendor_detail_coupons": "კუპონები",
    "vendor_detail_about": "შესახებ",
    "vendor_detail_reviews": "მიმოხილვები",
    "vendor_detail_polices": "პოლიცია",
    "vendor_detail_empty_description": "არ მიიღოთ გამყიდველის მონაცემები",
    "vendor_detail_empty_button": "Სახლში წასვლა",
    "vendor_detail_chat": "Სასაუბრო",
    "_post_wishlist_screen": "გამოაქვეყნეთ სურვილების სია",
    "post_wishlist_txt": "საყვარელი",
    "post_wishlist_notification_deleted": "{name} წაშლილია ფავორიტიდან",
    "post_wishlist_item": "{count} ელემენტი",
    "post_wishlist_items": "{count} ელემენტი",
    "post_wishlist_empty": "თქვენი რჩეული ცარიელია",
    "post_wishlist_empty_description": "უბრალოდ შედით სისტემაში, რომ გააგრძელოთ იქ, სადაც შეჩერდით.",
    "post_wishlist_btn_post_list": "ბლოგი ახლავე",
    "post": "პოსტები",
    "post_no_posts_were_found_matching": "შესატყვისი პოსტები ვერ მოიძებნა\nთქვენი არჩევანი.",
    "post_category": "კატეგორიის პოსტი",
    "_comment": "კომენტარები",
    "comment_s": "კომენტარები",
    "comment": "პასუხი",
    "comment_reply": "პასუხი",
    "comment_feedbacks": "{count} გამოხმაურება",
    "comment_feedback": "{count} გამოხმაურება",
    "comment_leave_a_reply": "დატოვეთ პასუხი",
    "comment_your_email_address_will": "თქვენი ელფოსტის მისამართი არ გამოქვეყნდება. აუცილებელი ველები მონიშნულია *",
    "comment_your_comments": "Თქვენი კომენტარები *",
    "comment_invalid_comment_content": "კომენტარის არასწორი შინაარსი",
    "comment_login_to_comment": "შედით კომენტარებში",
    "comment_tags": "ტეგები",
    "comment_show_more": "მეტის ჩვენება",
    "comment_post": "გამოაქვეყნეთ კომენტარები",
    "_product_category_screen": "პროდუქტების კატეგორია",
    "product_category": "კატეგორიები",
    "product_category_search": "პროდუქტების ძიება",
    "product_category_show_all": "Მაჩვენე ყველა",
    "product_category_item": "{count} ელემენტი",
    "product_category_items": "{count} ელემენტი",
    "product_category_no_found": "კატეგორიები ვერ მოიძებნა",
    "_brand_screen": "ბრენდი",
    "brand_title": "ყველა ბრენდი",
    "brand_search": "ბრენდის ძებნა",
    "brand_cancel": "გაუქმება",
    "brand_empty": "ცარიელი მონაცემები",
    "_on_boarding_screen": "ჩასხდომაზე",
    "on_boarding_skip": "გამოტოვება",
    "on_boarding_next": "შემდეგი",
    "on_boarding_get_start": "დაწყება",
    "_notifications": "შეტყობინება",
    "notifications_list_title": "ინბოქსის შეტყობინება",
    "notifications_list_delete": "1 შეტყობინება წაიშალა!",
    "notifications_list_dialog_title": "წაშალეთ შეტყობინებები",
    "notifications_list_dialog_description": "შეტყობინებები სამუდამოდ წაიშლება.",
    "notifications_list_dialog_cancel": "გაუქმება",
    "notifications_list_dialog_ok": "კარგი",
    "_notifications_detail": "შეტყობინების დეტალი",
    "notifications_detail_title": "შეტყობინების დეტალი",
    "notifications_detail_delete": "წაშლა",
    "notifications_detail_dialog_title": "შეტყობინების წაშლა",
    "notifications_detail_dialog_description": "შეტყობინება სამუდამოდ წაიშლება.",
    "notifications_detail_dialog_cancel": "გაუქმება",
    "notifications_detail_dialog_ok": "კარგი",
    "notifications_no": "შეტყობინებები არ არის",
    "notifications_you_currently": "თქვენ ამჟამად არ გაქვთ შეტყობინებები",
    "notifications_back": "უკან",
    "_profile": "პროფილი",
    "profile_txt": "პროფილი",
    "profile_account_txt": "ანგარიში",
    "profile_wallet_txt": "საფულე",
    "_location": "მდებარეობა",
    "location_txt": "მდებარეობა",
    "location_current_location": "გამოიყენე ჩემი ამჟამინდელი მდებარეობა",
    "location_saved": "შენახულია",
    "location_button_add_address": "Ახალი მისამართი",
    "location_address_home": "მთავარი",
    "location_address_office": "ოფისი",
    "select_location_txt": "აირჩიეთ მდებარეობა",
    "select_location_button_select": "აირჩიეთ",
    "select_location_near_place": "მიმდებარე ადგილი",
    "form_location_add_txt": "Ახალი მისამართი",
    "form_location_edit_txt": "მისამართის რედაქტირება",
    "form_location_address": "მისამართი",
    "form_location_add_address": "მისამართის დამატება",
    "form_location_default_address": "ნაგულისხმევი მისამართი",
    "form_location_tag_home": "მთავარი",
    "form_location_tag_office": "ოფისი",
    "form_location_tag_other": "სხვა",
    "form_location_button": "Გადარჩენა",
    "form_location_field_name": "სახელი",
    "form_location_delete_dialog_title": "მდებარეობის წაშლა",
    "form_location_delete_dialog_content": "მდებარეობა სამუდამოდ წაიშლება.",
    "form_location_delete_dialog_cancel": "გაუქმება",
    "form_location_delete_dialog_ok": "კარგი",
    "search_recent": "ბოლო ძიებები",
    "search_clear_all": "Ყველაფრის გასუფთავება",
    "search_you_are_turning_off_location_access": "თქვენ გამორთავთ მდებარეობაზე წვდომას",
    "search_allowing": "მდებარეობაზე წვდომის დაშვება დაგეხმარებათ სწორი მისამართის და მიწოდების დრაივერის უფრო სწრაფად და ზუსტად დადგენაში",
    "search_guide": "{appName} არ აქვს თქვენი მდებარეობის გამოყენების ნებართვა.",
    "required_location": "ჩართეთ მდებარეობის სერვისები, რათა „ {appName} “-მა დაადგინოს თქვენი მდებარეობა",
    "cancel": "გაუქმება",
    "setting": "დაყენება",
    "ok": "OK",
    "search_allow_btn": "მდებარეობაზე წვდომის დაშვება",
    "search_enter_btn": "შეიყვანეთ ჩემი მდებარეობა",
    "search_location": "მდებარეობის ძიება",
    "search_enter_your_address": "შეიყვანეთ თქვენი მისამართი",
    "search_select_location": "აირჩიეთ თქვენი მდებარეობა...",
    "search_select_looking_location": "ვეძებთ თქვენს მდებარეობას...",
    "_wallet_screen": "საფულე",
    "wallet_txt": "Ჩემი საფულე",
    "wallet_balance_subtitle": "საფულის ამჟამინდელი ბალანსი",
    "wallet_date": "თარიღი: {date}",
    "wallet_debit": "Სადებეტო",
    "wallet_credit": "კრედიტი",
    "_chat_detail_screen": "Სასაუბრო",
    "chat_detail_txt": "გამყიდველის ჩატი",
    "chat_detail_online": "ონლაინ",
    "chat_detail_empty": "არ არსებობს გამყიდველი",
    "chat_detail_return_home": "სახლში დაბრუნება",
    "_checkout_screen": "გადახდა",
    "checkout_billing_detail": "ბილინგის დეტალები",
    "checkout_shipping_address": "სხვა მისამართზე გაგზავნა?",
    "checkout_subtotal": "სუბტოტალი",
    "checkout_vat": "დღგ",
    "checkout_total": "სულ",
    "checkout_payment_method": "Გადახდის საშუალება",
    "checkout_billing_address": "ბილინგის მისამართი",
    "checkout_note": "შენიშვნა",
    "checkout_edit_address": "მისამართის რედაქტირება",
    "checkout_payment_confirm": "გადახდის დადასტურება",
    "checkout_order_id": "შეკვეთის ID: # {id}",
    "checkout_confirm": "დაადასტურეთ",
    "checkout_card_information": "ბარათის ინფორმაცია",
    "checkout_payment_price": "გადახდა {price}",
    "checkout_back": "უკან",
    "checkout_payment": "გადახდა",
    "checkout_input_address_book": "მისამართების წიგნი (სურვილისამებრ)",
    "checkout_new_address": "Ახალი მისამართი",
    "checkout_copy_address": "დააკოპირეთ მისამართი",
    "checkout_customer": "კლიენტი:",
    "_point_sale_screen": "პუნქტის გაყიდვა",
    "point_sale_txt": "პუნქტიანი გაყიდვა",
    "point_sale_layout": "განლაგება",
    "point_sale_layout_grid": "ბადე",
    "point_sale_layout_rect": "მართკუთხა",
    "point_sale_layout_list": "სია",
    "point_sale_sort_id": "ნაგულისხმევი",
    "point_sale_sort_title": "სახელი",
    "point_sale_sort_price": "ფასი",
    "point_sale_sort_date": "Თარიღი დამატებულია",
    "point_sale_sort_popularity": "პოპულარობა",
    "point_sale_descending": "Დაღმავალი",
    "point_sale_ascending": "აღმავალი",
    "point_sale_products": "პროდუქტები",
    "point_sale_orders": "შეკვეთები",
    "point_sale_add_customer": "დაამატეთ კლიენტი",
    "point_sale_update_customer": "განაახლეთ კლიენტი",
    "point_sale_add_customer_success": "კლიენტის დამატება წარმატებით",
    "point_sale_update_customer_success": "კლიენტის წარმატებით განახლება",
    "point_sale_add_new_customer": "დაამატეთ {text} ახალ მომხმარებელს",
    "point_sale_search_customer": "მოძებნეთ კლიენტი",
    "point_sale_save_customer": "გადაარჩინე მომხმარებელი",
    "point_sale_username": "მომხმარებლის სახელი",
    "_other": "სხვა",
    "listing_excilent": "EXCILE",
    "confirm_clean_cart_heading": "ენის შეცვლა?",
    "confirm_clean_cart_description": "კალათა სუფთა იქნება, თუ ენას შეცვლით.",
    "confirm_clean_cart_ok": "Კარგი",
    "confirm_clean_cart_cancel": "გაუქმება",
    "_clear_cache": "Ქეშის გაწმენდა",
    "clear_cache_heading": "Ქეშის გაწმენდა",
    "clear_cache_description": "დარწმუნებული ხართ, რომ გსურთ ქეშის გასუფთავება?",
    "clear_cache_yes": "დიახ",
    "clear_cache_cancel": "გაუქმება",
    "clear_cache_bytes": "{size} ბაიტი",
    "_captcha": "კაპჩა",
    "captcha_txt": "კაპჩა",
    "captcha_submit": "გაგზავნა",
    "captcha_error": "შეცდომა Captcha",
    "captcha_validate_empty": "ველის შევსება",
    "_address_book": "Მისამართების წიგნი",
    "address_book_txt": "Მისამართების წიგნი",
    "address_book_billing": "ბილინგის მისამართი",
    "address_book_shipping": "Მიწოდების მისამართი",
    "address_book_billing_book": "ბილინგის მისამართების წიგნი",
    "address_book_shipping_book": "მიწოდების მისამართების წიგნი",
    "address_book_address_empty": "ამ ტიპის მისამართი ჯერ არ დაგიყენებიათ.",
    "address_book_action": "მოქმედება",
    "address_book_edit": "რედაქტირება",
    "address_book_delete": "წაშლა",
    "address_book_primary": "Აქციე ძირითადად",
    "address_book_add_form_txt": "მისამართის დამატება",
    "address_book_edit_form_txt": "მისამართის განახლება",
    "address_book_input_nickname": "მისამართი მეტსახელი (არასავალდებულო)",
    "address_book_hint_nickname": "დაგეხმარებათ ადვილად ამოიცნოთ თქვენი მისამართები.",
    "address_book_add_success_form": "დაამატეთ მისამართი წარმატება",
    "address_book_update_success_form": "მისამართის განახლება წარმატებით დასრულდა",
    "_picker": "ამომრჩევი",
    "picker_select_file": "Მონიშნე ფაილი",
    "picker_change_file": "ფაილის შეცვლა",
    "picker_no_file": "Ფაილი არ არის არჩეული",
    "picker_take_photo": "Ფოტოს გადაღება",
    "picker_photo_library": "ფოტო ბიბლიოთეკა",
    "picker_file_library": "ფაილების ბიბლიოთეკა",
    "picker_remove_file": "ფაილის წაშლა",
    "picker_cancel": "გაუქმება",
    "_buddypress_screen": "ბადიპრესი",
    "buddypress_compose": "შედგენა",
    "buddypress_compose_reset": "გადატვირთვა",
    "buddypress_compose_subject": "საგანი",
    "buddypress_compose_message": "შეტყობინება",
    "buddypress_compose_send": "გაგზავნა",
    "buddypress_compose_send_empty": "აირჩიეთ გაგზავნა",
    "buddypress_compose_success": "შედგენა წარმატებით",
    "buddypress_create_private_message_success": "პირადი შეტყობინების შექმნა წარმატებით",
    "buddypress_chat_message_empty_conversation": "ID ცარიელია",
    "buddypress_chat_message_error": "შეცდომა",
    "buddypress_chat_message_send": "გაგზავნა:",
    "buddypress_chat_message_send_add": "დამატება",
    "buddypress_chat_message_send_delete": "წაშლა",
    "buddypress_forums": "ბადიპრესის ფორუმები",
    "buddypress_forums_topic_started": "თემები დაიწყო",
    "buddypress_forums_reply_created": "პასუხები შექმნილია",
    "buddypress_forums_engagement": "ნიშნობა",
    "buddypress_forums_favorite": "რჩეულები",
    "buddypress_group_detail": "ბადიპრესის ჯგუფის დეტალები",
    "buddypress_group_list": "ბადიპრესის ჯგუფები",
    "buddypress_member_detail": "Buddypress წევრის დეტალები",
    "buddypress_member_list": "ბადიპრესის წევრები",
    "buddypress_message_list": "ბადიპრესის შეტყობინებები",
    "buddypress_message_list_inbox": "Შემომავალი",
    "buddypress_message_list_starred": "ვარსკვლავიანი",
    "buddypress_message_list_sent": "Გაგზავნილი",
    "buddypress_create_activity": "შექმენით აქტივობა",
    "buddypress_create_activity_success": "შექმენით ახალი აქტივობა წარმატებით",
    "buddypress_create_publish_message_success": "შექმენით გამოქვეყნებული შეტყობინება წარმატებით",
    "buddypress_comments": "კომენტარები",
    "buddypress_comment": "კომენტარი",
    "buddypress_comment_reply": "პასუხი # {secondaryId} # {primaryId} -ში",
    "buddypress_comment_list_error_id": "შეცდომის ID",
    "buddypress_comment_write": "დაწერეთ კომენტარი",
    "buddypress_create_comment_success": "დაწერეთ კომენტარი წარმატებით",
    "buddypress_create_comment_reply_success": "პასუხი წარმატებით",
    "buddypress_remove_favorite_activity_success": "#$ {id} მა წაშალა რჩეული წარმატება",
    "buddypress_add_favorite_activity_success": "#$ {id} მა დაამატა რჩეული წარმატება",
    "buddypress_group": "ჯგუფი",
    "buddypress_group_activities": "Საქმიანობის",
    "buddypress_group_no": "არ მიიღოთ პირადობის მოწმობა",
    "buddypress_group_update_activity": "განახლების ახალი აქტივობა",
    "buddypress_group_update_activity_success": "ახალი განახლების აქტივობის წარმატება",
    "buddypress_friends": "Მეგობრები",
    "buddypress_friends_friendship": "მეგობრობა",
    "buddypress_friends_request": "ითხოვს",
    "buddypress_friends_add": "დაამატეთ მეგობრობა",
    "buddypress_friends_cancel": "გააუქმე მეგობრობა",
    "buddypress_friends_cancel_request": "გააუქმეთ მეგობრობის მოთხოვნა",
    "buddypress_friends_requested": "მეგობრობა მოითხოვა",
    "buddypress_friends_accept": "მიღება",
    "buddypress_friends_reject": "Უარი თქვას",
    "buddypress_activity": "აქტივობა",
    "buddypress_messages": "შეტყობინებები",
    "buddypress_more": "მეტი",
    "buddypress_empty": "ცარიელი",
    "buddypress_from": "მდებარეობა:",
    "buddypress_and_single": "(და {count} სხვა)",
    "buddypress_and_multi": "(და {count} სხვა)",
    "buddypress_active": "აქტიურია {date}",
    "buddypress_join": "შეუერთდა {date}",
    "buddypress_private_group": "კერძო ჯგუფი",
    "buddypress_hidden_group": "დამალული ჯგუფი",
    "buddypress_public_group": "საზოგადოებრივი ჯგუფი",
    "buddypress_validate_empty": "ველის შევსება",
    "buddypress_content": "შინაარსი",
    "buddypress_post": "პოსტი",
    "buddypress_info": "ინფორმაცია",
    "buddypress_members": "წევრები",
    "buddypress_search": "ძიება",
    "buddypress_name": "სახელი",
    "buddypress_avatar": "ავატარი",
    "buddypress_status": "სტატუსი",
    "buddypress_description": "აღწერა",
    "buddypress_create_at": "შექმნილია",
    "buddypress_last_active": "ბოლო აქტიური",
    "buddypress_newest_register": "უახლესი დარეგისტრირებული",
    "buddypress_alphabetical": "ანბანური",
    "buddypress_most_member": "წევრების უმეტესობა",
    "buddypress_new_created": "ახლად შექმნილი",
    "buddypress_all": "ყველა",
    "buddypress_new_member": "ახალი წევრები",
    "buddypress_profile_update": "პროფილის განახლებები",
    "buddypress_update": "განახლებები",
    "buddypress_friendship": "მეგობრობა",
    "buddypress_new_group": "ახალი ჯგუფები",
    "buddypress_group_member": "ჯგუფის წევრობები",
    "buddypress_group_update": "ჯგუფის განახლებები",
    "buddypress_topics": "თემები",
    "buddypress_replies": "პასუხები",
    "buddypress_sign_in": "Შებრძანდით",
    "buddypress_required_login": "გამოყენებული უნდა შეხვიდეთ",
    "buddypress_profile": "პროფილი",
    "buddypress_publish_message": "შეტყობინების გამოქვეყნება",
    "buddypress_private_message": "Პირადი შეტყობინება",
    "buddypress_username": "მომხმარებლის სახელი",
    "buddypress_filter": "ფილტრი",
    "buddypress_no_active": "ახლახან არ არის აქტიური",
    "buddypress_member_no": "არ მიიღოთ პირადობის მოწმობის წევრი",
    "buddypress_register_since": "მას შემდეგ დარეგისტრირდა",
    "_bbpress_screen": "bbPress",
    "bbpress_forum_list": "ფორუმები",
    "bbpress_forum_detail": "ფორუმი",
    "bbpress_topic_detail": "Თემა",
    "bbpress_create_topic": "ახალი თემის შექმნა",
    "bbpress_create_topic_title": "სათაური",
    "bbpress_create_topic_content": "შინაარსი",
    "bbpress_create_topic_tag": "ტეგები",
    "bbpress_create_topic_type": "ტიპი",
    "bbpress_create_topic_status": "სტატუსი",
    "bbpress_create_topic_notify_email": "შემატყობინე შემდგომი პასუხების შესახებ ელფოსტით",
    "bbpress_create_topic_submit": "გაგზავნა",
    "bbpress_create_topic_unstick": "ნორმალური",
    "bbpress_create_topic_stick": "წებოვანი",
    "bbpress_create_topic_super": "სუპერ წებოვანი",
    "bbpress_create_topic_status_publish": "გახსენით",
    "bbpress_create_topic_status_closed": "დახურულია",
    "bbpress_create_topic_status_spam": "Სპამი",
    "bbpress_create_topic_status_trash": "ნაგავი",
    "bbpress_create_topic_status_pending": "მომლოდინე",
    "bbpress_create_topic_success": "შექმენით ახალი თემა წარმატებით",
    "bbpress_create_reply_success": "შექმენით ახალი პასუხი წარმატებით",
    "bbpress_topics": "თემები",
    "bbpress_replies": "პასუხები",
    "bbpress_started_by": "დაიწყო",
    "bbpress_by": "მიერ",
    "bbpress_in": "in",
    "bbpress_reply": "პასუხი",
    "bbpress_replies_in": "პასუხები:",
    "bbpress_count_post_single": "{count} პოსტი",
    "bbpress_count_post_multi": "{count} პოსტი",
    "bbpress_count_topic_single": "{count} თემა",
    "bbpress_count_topic_multi": "{count} თემა",
    "bbpress_count_no_topic": "არავითარი თემა",
    "bbpress_forum_no": "ფორუმზე ვერ ვიღებ",
    "bbpress_topic_no": "თემის აღება ვერ ხერხდება",
    "bm_participants_count": "{count} მონაწილე",
    "bm_create_conversation": "დაიწყეთ ახალი საუბარი",
    "bm_current_conversation": "&quot; {name} &quot;-ის მიმდინარე საუბრები",
    "bm_participants": "Მონაწილეები",
    "_timeago": "დროის წინ",
    "timeago_ago": "წინ",
    "timeago_from_now": "დღეიდან",
    "timeago_less_a_minute": "მომენტი",
    "timeago_a_minute": "ერთი წუთი",
    "timeago_minutes": "{minutes} წუთი",
    "timeago_an_hour": "დაახლოებით ერთი საათი",
    "timeago_hours": "{hours} საათი",
    "timeago_a_day": "დღე",
    "timeago_days": "{days} დღე",
    "timeago_a_month": "დაახლოებით ერთი თვე",
    "timeago_months": "{months} თვე",
    "timeago_a_year": "დაახლოებით ერთი წელი",
    "timeago_years": "{years} წელი",
    "_internet": "ინტერნეტი",
    "no_internet": "Არ არის ინტერნეტ კავშირი",
    "no_internet_content_1": "ჩვენ ვერ აღმოვაჩენთ რაიმე ინტერნეტ დაკავშირებას. გთხოვთ, შეამოწმოთ თქვენი ინტერნეტ კავშირი და ხელახლა გახსენით აპლიკაცია.",
    "no_internet_content_2": "ჩვენ ვერ აღმოვაჩენთ რაიმე ინტერნეტ დაკავშირებას. გთხოვთ, შეამოწმოთ თქვენი ინტერნეტ კავშირი.",
    "internet_connected": "ინტერნეტთან დაკავშირებული",
    "internet_let": "ვისიამოვნოთ.",
    "vendor_rated": "რეიტინგული",
    "you_must_login": "თქვენ უნდა შეხვიდეთ"
}